Workbook

Sheet Sales
A1: Order ID | B1: Date | C1: Salesperson | D1: Product ID | E1: Region | F1: Units Sold | G1: Payment Mode | H1: Sales Amount | I1: ProductName | J1: Category | K1: Unit Price
A2: 1001 | B2: 45292 | C2: Rahul | D2: P101 | E2: North | F2: 5 | G2: Card | H2: =F2*K2 -> 300000 | I2: =VLOOKUP(D2,Product!A1:D6,2,0) -> Laptop | J2: =VLOOKUP(D2,Product!A:D,3,0) -> Electronics | K2: =VLOOKUP(D2,Product!A:D,4,0) -> 60000
A3: 1002 | B3: 45292 | C3: Priya | D3: P102 | E3: South | F3: 10 | G3: UPI | H3: =F3*K3 -> 200000 | I3: =VLOOKUP(D3,Product!A2:D7,2,0) -> Phone | J3: =VLOOKUP(D3,Product!A:D,3,0) -> Electronics | K3: =VLOOKUP(D3,Product!A:D,4,0) -> 20000
A4: 1003 | B4: 45293 | C4: Amit | D4: P103 | E4: West | F4: 15 | G4: Cash | H4: =F4*K4 -> 60000 | I4: =VLOOKUP(D4,Product!A3:D8,2,0) -> Chair | J4: =VLOOKUP(D4,Product!A:D,3,0) -> Furniture | K4: =VLOOKUP(D4,Product!A:D,4,0) -> 4000
A5: 1004 | B5: 45293 | C5: Neha | D5: P104 | E5: East | F5: 7 | G5: Card | H5: =F5*K5 -> 49000 | I5: =VLOOKUP(D5,Product!A4:D9,2,0) -> Table | J5: =VLOOKUP(D5,Product!A:D,3,0) -> Furniture | K5: =VLOOKUP(D5,Product!A:D,4,0) -> 7000
A6: 1005 | B6: 45294 | C6: Rahul | D6: P102 | E6: North | F6: 8 | G6: UPI | H6: =F6*K6 -> 160000 | I6: =VLOOKUP(D3,Product!A:D,2,0) -> Phone | J6: =VLOOKUP(D6,Product!A:D,3,0) -> Electronics | K6: =VLOOKUP(D6,Product!A:D,4,0) -> 20000
A7: 1006 | B7: 45294 | C7: Priya | D7: P101 | E7: South | F7: 4 | G7: Card | H7: =F7*K7 -> 240000 | I7: =VLOOKUP(D7,Product!A:D,2,0) -> Laptop | J7: =VLOOKUP(D7,Product!A:D,3,0) -> Electronics | K7: =VLOOKUP(D7,Product!A:D,4,0) -> 60000
A8: 1007 | B8: 45295 | C8: Amit | D8: P105 | E8: West | F8: 6 | G8: Cash | H8: =F8*K8 -> 54000 | I8: =VLOOKUP(D8,Product!A:D,2,0) -> Desk | J8: =VLOOKUP(D8,Product!A:D,3,0) -> Furniture | K8: =VLOOKUP(D8,Product!A:D,4,0) -> 9000
A9: 1008 | B9: 45295 | C9: Neha | D9: P102 | E9: East | F9: 12 | G9: UPI | H9: =F9*K9 -> 240000 | I9: =VLOOKUP(D9,Product!A:D,2,0) -> Phone | J9: =VLOOKUP(D9,Product!A:D,3,0) -> Electronics | K9: =VLOOKUP(D9,Product!A:D,4,0) -> 20000
A10: 1009 | B10: 45296 | C10: Rahul | D10: P103 | E10: North | F10: 20 | G10: Cash | H10: =F10*K10 -> 80000 | I10: =VLOOKUP(D10,Product!A:D,2,0) -> Chair | J10: =VLOOKUP(D10,Product!A:D,3,0) -> Furniture | K10: =VLOOKUP(D10,Product!A:D,4,0) -> 4000
A11: 1010 | B11: 45296 | C11: Priya | D11: P102 | E11: South | F11: 9 | G11: Card | H11: =F11*K11 -> 180000 | I11: =VLOOKUP(D11,Product!A:D,2,0) -> Phone | J11: =VLOOKUP(D11,Product!A:D,3,0) -> Electronics | K11: =VLOOKUP(D11,Product!A:D,4,0) -> 20000
A14: SUMIF
A16: Total Sales Amount of North
A17: =SUMIF(E2:E11,"North",H2:H11) -> 540000
A19: Total Units Sold for Product Phone
A20: =SUMIF(D1:D11,"P102",F1:F11) -> 39
A22: COUNTIF
A24: No.of Transacions using UPI
A25: =COUNTIF(G1:G11,"UPI") -> 3
A27: No. of Transactions from South
A28: =COUNTIF(E1:E11,"South") -> 3
A30: SUMIFS
A33: Total Sales Amount for Electronics category in North region
A34: =SUMIFS(H2:H11,E2:E11,"North",D2:D11,"P101")+SUMIFS(H2:H11,E2:E11,"North",D2:D11,"P102") -> 460000
A36: Total Units Sold for Furniture category in West region
A37: =SUMIFS(F2:F11,E2:E11,"West",D2:D11,"P103")+SUMIFS(F2:F11,E2:E11,"West",D2:D11,"P105") -> 21
A39: COUNTIFS
A41: No.of Transactions for Electronics using Card
A42: =COUNTIFS(J2:J11,"Electronics",G2:G11,"Card") -> 3
A44: No. of Transactions in North Region for Furniture
A45: =COUNTIFS(E2:E11,"North",J2:J11,"Furniture") -> 1

Sheet Product
A1: Product ID | B1: Product Name | C1: Category | D1: Unit Price
A2: P101 | B2: Laptop | C2: Electronics | D2: 60000
A3: P102 | B3: Phone | C3: Electronics | D3: 20000
A4: P103 | B4: Chair | C4: Furniture | D4: 4000
A5: P104 | B5: Table | C5: Furniture | D5: 7000
A6: P105 | B6: Desk | C6: Furniture | D6: 9000

Sheet Pivot Table 
A1: SUM of Sales Amount | B1: Category
A2: Region | B2: Electronics | C2: Furniture | D2: Grand Total
A3: East | B3: 240000 | C3: 49000 | D3: 289000
A4: North | B4: 460000 | C4: 80000 | D4: 540000
A5: South | B5: 620000 | D5: 620000
A6: West | C6: 114000 | D6: 114000
A7: Grand Total | B7: 1320000 | C7: 243000 | D7: 1563000
A10: Which Region generated the highest Sales?
A11: South
A13: Which category generated the highest sales?
A14: Electronics
